rock/__init__.py
rock/lib/__init__.py
rock/lib/corr.py
rock/lib/plots.py
rock/lib/useful.py
rock_pre_h-0.1.5.dist-info/LICENSE.txt
rock_pre_h-0.1.5.dist-info/METADATA
rock_pre_h-0.1.5.dist-info/WHEEL
rock_pre_h-0.1.5.dist-info/top_level.txt
rock_pre_h-0.1.5.dist-info/RECORD
