Metadata-Version: 2.1
Name: rock-pre-h
Version: 0.1.5
Summary: rock-for-easy-preprocessing
Home-page: https://github.com/lakP44/we_are_always_APA/tree/main/rock
Author: P444
Author-email: laklak5000@gmail.com
Requires-Python: >=3.9.13
License-File: LICENSE.txt
Requires-Dist: matplotlib (==3.5.2)
Requires-Dist: numpy (==1.21.5)
Requires-Dist: pandas (==1.4.4)
Requires-Dist: scikit-learn (==1.2.0)
Requires-Dist: scipy (==1.9.1)
Requires-Dist: seaborn (==0.11.2)
Requires-Dist: setuptools (==63.4.1)
